all_in_one_fix-2.0.4.dist-info/licenses/LICENSE
all_in_one_fix-2.0.4.dist-info/licenses/NOTICE
allin1fix/__about__.py
allin1fix/__init__.py
allin1fix/_install_madmom.py
allin1fix/analyze.py
allin1fix/cli.py
allin1fix/config.py
allin1fix/demix.py
allin1fix/helpers.py
allin1fix/sonify.py
allin1fix/spectrogram.py
allin1fix/stems.py
allin1fix/stems_input.py
allin1fix/typings.py
allin1fix/utils.py
allin1fix/visualize.py
allin1fix/models/__init__.py
allin1fix/models/allinone.py
allin1fix/models/dinat.py
allin1fix/models/ensemble.py
allin1fix/models/loaders.py
allin1fix/models/utils.py
allin1fix/postprocessing/__init__.py
allin1fix/postprocessing/functional.py
allin1fix/postprocessing/helpers.py
allin1fix/postprocessing/metrical.py
allin1fix/postprocessing/tempo.py
allin1fix/training/__init__.py
allin1fix/training/evaluate.py
allin1fix/training/helpers.py
allin1fix/training/preprocess.py
allin1fix/training/train.py
allin1fix/training/trainer.py
allin1fix/training/data/__init__.py
allin1fix/training/data/utils.py
allin1fix/training/data/datasets/__init__.py
allin1fix/training/data/datasets/collate.py
allin1fix/training/data/datasets/datasetbase.py
allin1fix/training/data/datasets/harmonix/__init__.py
allin1fix/training/data/datasets/harmonix/datamodule.py
allin1fix/training/data/datasets/harmonix/dataset.py
allin1fix/training/data/eventconverters/__init__.py
allin1fix/training/data/eventconverters/datasetconverters.py
allin1fix/training/data/eventconverters/eventconverters.py
all_in_one_fix-2.0.4.dist-info/METADATA
all_in_one_fix-2.0.4.dist-info/WHEEL
all_in_one_fix-2.0.4.dist-info/entry_points.txt
all_in_one_fix-2.0.4.dist-info/top_level.txt
all_in_one_fix-2.0.4.dist-info/RECORD
