Metadata-Version: 2.4
Name: all-in-one-fix
Version: 2.0.4
Summary: All-In-One Music Structure Analyzer with source separation
Author-email: Taejun Kim <taejun@kaist.ac.kr>
Maintainer: Package Maintainers
License: MIT
Project-URL: Homepage, https://github.com/openmirlab/all-in-one-fix
Project-URL: Repository, https://github.com/openmirlab/all-in-one-fix
Project-URL: Documentation, https://github.com/openmirlab/all-in-one-fix#readme
Project-URL: Bug Reports, https://github.com/openmirlab/all-in-one-fix/issues
Project-URL: Original All-In-One, https://github.com/mir-aidj/all-in-one
Project-URL: Changelog, https://github.com/openmirlab/all-in-one-fix/blob/main/docs/CHANGELOG.md
Keywords: music,beat,downbeat,tracking,structure,analysis,allin1fix,source-separation
Classifier: Development Status :: 5 - Production/Stable
Classifier: Intended Audience :: Developers
Classifier: Intended Audience :: Science/Research
Classifier: License :: OSI Approved :: MIT License
Classifier: Operating System :: OS Independent
Classifier: Programming Language :: Python :: 3
Classifier: Programming Language :: Python :: 3.8
Classifier: Programming Language :: Python :: 3.9
Classifier: Programming Language :: Python :: 3.10
Classifier: Programming Language :: Python :: 3.11
Classifier: Programming Language :: Python :: 3.12
Classifier: Topic :: Multimedia :: Sound/Audio
Classifier: Topic :: Scientific/Engineering :: Artificial Intelligence
Requires-Python: >=3.9
License-File: LICENSE
License-File: NOTICE
Requires-Dist: numpy
Requires-Dist: librosa
Requires-Dist: torch<2.8.0,>=2.0.0
Requires-Dist: natten==0.17.5
Requires-Dist: hydra-core
Requires-Dist: omegaconf
Requires-Dist: huggingface_hub
Requires-Dist: matplotlib
Requires-Dist: scipy>=1.0.0
Requires-Dist: demucs-infer
Provides-Extra: train
Requires-Dist: lightning; extra == "train"
Requires-Dist: timm; extra == "train"
Requires-Dist: wandb; extra == "train"
Requires-Dist: mir_eval; extra == "train"
Requires-Dist: numpy<1.24; extra == "train"
Provides-Extra: dev
Requires-Dist: black; extra == "dev"
Requires-Dist: ruff; extra == "dev"
Dynamic: license-file
